metaimageio/__init__.py
metaimageio/imageio.py
metaimageio/reader.py
metaimageio/util.py
metaimageio/version.py
metaimageio/writer.py
metaimageio-1.3.2.dist-info/licenses/LICENSE.md
tests/conftest.py
tests/test_imageio.py
tests/test_io.py
tests/test_matlab.py
metaimageio-1.3.2.dist-info/METADATA
metaimageio-1.3.2.dist-info/WHEEL
metaimageio-1.3.2.dist-info/top_level.txt
metaimageio-1.3.2.dist-info/RECORD
