Metadata-Version: 2.4
Name: metaimageio
Version: 1.3.2
Summary: Support for reading and writing images in MetaIO file format.
Author: Ali Uneri
Project-URL: Homepage, https://auneri.github.io/MetaImageIO
Project-URL: Repository, https://github.com/auneri/MetaImageIO
Classifier: License :: OSI Approved :: MIT License
Classifier: Operating System :: OS Independent
Classifier: Programming Language :: Python :: 3
Requires-Python: >=3.8
License-File: LICENSE.md
Requires-Dist: numpy>=1.26
Provides-Extra: imageio
Requires-Dist: imageio>=2.28; extra == "imageio"
Provides-Extra: pytest
Requires-Dist: pytest; extra == "pytest"
Requires-Dist: pytest-cov; extra == "pytest"
Requires-Dist: pytest-ruff; extra == "pytest"
Dynamic: license-file
